dism_core/__init__.py
dism_core/_version.py
dism_core/template.py
dism_core/versions.py
dism_core/properties/__init__.py
dism_core/properties/base.py
dism_core/properties/isvc/__init__.py
dism_core/properties/isvc/base.py
dism_core/properties/isvc/inference_cond.py
dism_core/properties/isvc/metadata.py
dism_core/properties/isvc/resources.py
dism_core/properties/isvc/signature.py
dism_core/properties/isvc/mlserver/__init__.py
dism_core/properties/isvc/mlserver/base.py
dism_core/properties/isvc/mlserver/lightgbm.py
dism_core/properties/isvc/mlserver/sklearn.py
dism_core/properties/isvc/mlserver/xgboost.py
dism_core/properties/isvc/tritonserver/__init__.py
dism_core/properties/isvc/tritonserver/base.py
dism_core/properties/isvc/tritonserver/onnx.py
dism_core/properties/isvc/tritonserver/python.py
dism_core/properties/isvc/tritonserver/tensorflow_savedmodel.py
dism_core/properties/isvc/tritonserver/torchscript.py
dism_core/properties/isvc/tritonserver/types.py
dism_core/resources/__init__.py
dism_core/resources/types.py
dism_core/resources/isvc/__init__.py
dism_core/resources/isvc/resource.py
dism_core/resources/isvc/types.py
dism_core/validation/__init__.py
dism_core/validation/isvc.py
dism_core/validation/utils.py
dism_core-1.5.1.dist-info/licenses/LICENSE
dism_core-1.5.1.dist-info/METADATA
dism_core-1.5.1.dist-info/WHEEL
dism_core-1.5.1.dist-info/top_level.txt
dism_core-1.5.1.dist-info/RECORD
