Metadata-Version: 2.4
Name: dism-core
Version: 1.5.1
Summary: Validation tools for the yaml template used by DIALS Inference Service Manager.
Author-email: Gabriel Moreira <gabriel.moreira@cern.ch>
Classifier: Programming Language :: Python :: 3.9
Classifier: Programming Language :: Python :: 3.10
Classifier: Programming Language :: Python :: 3.11
Classifier: Programming Language :: Python :: 3.12
Classifier: Development Status :: 5 - Production/Stable
Classifier: Environment :: Console
Requires-Python: >=3.9
License-File: LICENSE
Requires-Dist: pydantic<3.0.0,>=2.8.2
Requires-Dist: pyyaml<7.0.0,>=5.4.1
Dynamic: license-file
